hark/__init__.py
hark/__main__.py
hark/audio_sources.py
hark/cli.py
hark/config.py
hark/constants.py
hark/device.py
hark/diarizer.py
hark/exceptions.py
hark/formatter.py
hark/interactive.py
hark/keypress.py
hark/platform.py
hark/preprocessor.py
hark/stereo_processor.py
hark/transcriber.py
hark/ui.py
hark/utils.py
hark/audio_backends/__init__.py
hark/audio_backends/base.py
hark/audio_backends/coreaudio.py
hark/audio_backends/pulseaudio.py
hark/audio_backends/wasapi.py
hark/backends/__init__.py
hark/backends/base.py
hark/backends/whisper.py
hark/backends/whisperx.py
hark/recorder/__init__.py
hark/recorder/file_manager.py
hark/recorder/interleaver.py
hark/recorder/recorder.py
hark/recorder/types.py
hark_cli-0.3.0.dist-info/METADATA
hark_cli-0.3.0.dist-info/WHEEL
hark_cli-0.3.0.dist-info/entry_points.txt
hark_cli-0.3.0.dist-info/licenses/LICENSE
hark_cli-0.3.0.dist-info/RECORD
