Metadata-Version: 2.4
Name: hark-cli
Version: 0.3.0
Summary: 100% offline, Whisper-powered voice notes from your terminal
Project-URL: Homepage, https://github.com/FPurchess/hark
Project-URL: Repository, https://github.com/FPurchess/hark
Project-URL: Issues, https://github.com/FPurchess/hark/issues
License: AGPL-3.0-or-later
License-File: LICENSE
Keywords: cli,faster-whisper,offline,speech-to-text,transcription,voice-notes,whisper
Classifier: Development Status :: 3 - Alpha
Classifier: Environment :: Console
Classifier: Intended Audience :: End Users/Desktop
Classifier: License :: OSI Approved :: GNU Affero General Public License v3 or later (AGPLv3+)
Classifier: Operating System :: MacOS
Classifier: Operating System :: Microsoft :: Windows :: Windows 10
Classifier: Operating System :: Microsoft :: Windows :: Windows 11
Classifier: Operating System :: POSIX :: Linux
Classifier: Programming Language :: Python :: 3.11
Classifier: Programming Language :: Python :: 3.12
Classifier: Programming Language :: Python :: 3.13
Classifier: Topic :: Multimedia :: Sound/Audio :: Speech
Requires-Python: >=3.11
Requires-Dist: faster-whisper>=1.0.0
Requires-Dist: librosa>=0.10.0
Requires-Dist: noisereduce>=3.0.0
Requires-Dist: numpy>=1.24.0
Requires-Dist: pulsectl>=24.0.0; sys_platform == 'linux'
Requires-Dist: pyaudiowpatch>=0.2.12.7; sys_platform == 'win32'
Requires-Dist: pyyaml>=6.0.1
Requires-Dist: sounddevice>=0.5.0
Requires-Dist: soundfile>=0.12.0
Provides-Extra: dev
Requires-Dist: pre-commit>=3.0.0; extra == 'dev'
Requires-Dist: pyrefly>=0.45.0; extra == 'dev'
Requires-Dist: pytest-cov>=4.0.0; extra == 'dev'
Requires-Dist: pytest>=7.0.0; extra == 'dev'
Requires-Dist: ruff>=0.1.0; extra == 'dev'
Requires-Dist: whisperx>=3.1.0; extra == 'dev'
Provides-Extra: diarization
Requires-Dist: whisperx>=3.1.0; extra == 'diarization'
Provides-Extra: test
Requires-Dist: pre-commit>=3.0.0; extra == 'test'
Requires-Dist: pyrefly>=0.45.0; extra == 'test'
Requires-Dist: pytest-cov>=4.0.0; extra == 'test'
Requires-Dist: pytest>=7.0.0; extra == 'test'
Requires-Dist: ruff>=0.1.0; extra == 'test'
Requires-Dist: whisperx>=3.1.0; extra == 'test'
